Workbook

Sheet Financial Model
A1: Calgary Food Bank
A2: Break-Even Analysis
A4: Total Fixed Costs | B4: =SUM('Income Statement'!B30:B35) -> 410000
A5: Total Variable Costs | B5: ='Income Statement'!B29+'Income Statement'!B36 -> 875000
A6: Total Revenue | B6: =SUM('Income Statement'!B2:B5) -> 2300000
A9: Variable Cost Ratio | B9: =B5/B6 -> 0.38043478 | C9: 875,000/2,300,000
A10: Contribution Margin Ratio | B10: =1-B9 -> 0.61956522 | C10: 1-0.38
A12: Break-Even Revenue | B12: =B4/B10 -> 661754.39 | C12: 410000/0.62
A14: Current Revenue | B14: =B6 -> 2300000
A15: Safety Margin (%) | B15: =(B6-B12)/B14 -> 0.7122807 | C15: 2300000-661,754.39
A17: Key Metrics
A18: Operating Expense Ratio | B18: ='Income Statement'!B37/'Income Statement'!B26 -> 0.55869565 | C18: 1,285,000 / 2,300,000
A19: Revenue per Dollar Donated (CFB Efficiency) | B19: =('Income Statement'!B2+'Income Statement'!B3)/'Income Statement'!B2 -> 1.5 | C19: 1,200,000+600,000 / 1,200,000
A20: Admin Cost Ratio | B20: ='Income Statement'!B12/'Income Statement'!B26 -> 0.02173913 | C20: 50,000 / 2,300,000
A21: Program Cost Ratio | B21: =('Income Statement'!B7+'Income Statement'!B14)/'Income Statement'!B26 -> 0.38043478 | C21: 800,000+75,000 / 2,300,000

Sheet Income Statement
A1: ASSUMPTIONS
A2: Annual Monetary Donations | B2: 1200000
A3: In-Kind Food Donations (Value) | B3: 600000
A4: Grant Funding | B4: 400000
A5: Other Revenue (Events, etc.) | B5: 100000
A7: Staff Costs (Annual) | B7: 800000 | C7: Variable
A8: Facility Rent/Lease | B8: 150000 | C8: Fixed
A9: Utilities & Maintenance | B9: 80000 | C9: Fixed
A10: Vehicles & Transportation | B10: 60000 | C10: Fixed
A11: Technology & Systems | B11: 40000 | C11: Fixed
A12: Administration & Office | B12: 50000 | C12: Fixed
A13: Marketing & Outreach | B13: 30000 | C13: Fixed
A14: Food Storage & Distribution | B14: 75000 | C14: Variable
A18: Calgary Food Bank
A19: Income Statement
A20: For the year ended December 31,2022
A21: Revenue
A22: Monetary Donations | B22: =B2 -> 1200000
A23: In-Kind Food Donations | B23: =B3 -> 600000
A24: Grant Funding | B24: =B4 -> 400000
A25: Other Revenue | B25: =B5 -> 100000
A26: Total Revenue | B26: =SUM(B22:B25) -> 2300000
A28: Operating Expenses
A29: Staff Costs | B29: =B7 -> 800000
A30: Facility Rent/Lease | B30: =B8 -> 150000
A31: Utilities & Maintenance | B31: =B9 -> 80000
A32: Vehicles & Transportation | B32: =B10 -> 60000
A33: Technology & Systems | B33: =B11 -> 40000
A34: Administration & Office | B34: =B12 -> 50000
A35: Marketing & Outreach | B35: =B13 -> 30000
A36: Food Storage & Distribution | B36: =B14 -> 75000
A37: Total Operating | B37: =SUM(B29:B36) -> 1285000
A39: Net Income (Surplus/Deficit) | B39: =B26-B37 -> 1015000
A40: Net Profit Margin | B40: =B39/B26 -> 0.44130435 | C40: 2,300,000/1,285,000

Sheet Balance Sheet
A1: Calgary Food Bank
A2: Balance Sheet
A3: As of December 31,2024
A4: Assets
A5: Current Assets
A6: Cash and Cash Equivalents | B6: 750000
A7: Accounts Receivable | B7: 150000
A8: Food Inventory | B8: 160000
A9: Supplies & Materials | B9: =75000 -> 75000
A10: Total Current Assets | B10: =SUM(B6:B9) -> 1135000
A12: Fixed Assets
A13: Equipment & Vehicles | B13: =500000+5000 -> 505000
A14: Less: Accumulated Depreciation | B14: -180000
A15: Net Fixed Assets | B15: =SUM(B13:B14) -> 325000
A17: Other Assets
A18: Prepaid Expenses & Other | B18: 120000
A19: Accumulated Donations / Grants | B19: =470000 -> 470000
A20: Total Other Assets | B20: =SUM(B18:B19) -> 590000
A22: Total Assets | B22: =B10+B15+B20 -> 2050000
A24: Liabilities & Owner's Equity
A25: Current Liabilities
A26: Accounts Payable | B26: 125000
A27: Accrued Expenses | B27: 150000
A28: Current Portion of Debt | B28: 20000
A29: Total Current Liabilities | B29: =SUM(B26:B28) -> 295000
A31: Long-Term Liabilities
A32: Long-Term Debt | B32: 140000
A34: Total Liabilities | B34: =B29+B32 -> 435000
A36: Owner's Equity
A37: Owner's Equity (Opening Balance) | B37: 600000
A38: Add: Current Year Surplus from Operations | B38: ='Income Statement'!B39 -> 1015000
A40: Total Owner's Equity | B40: =B37+B38 -> 1615000
A42: Total Liability & Owner's Equity | B42: =B34+B40 -> 2050000

Sheet Cash Flow Statement
A1: Calgary Food Bank
A2: Statement of Cash Flow
A3: For the Month Ended Dec,31,2023
A4: OPERATING ACTIVITIES
A5: Net Income | B5: ='Income Statement'!B39 -> 1015000
A7: Adjustments to reconcile net income to cash:
A8: Depreciation Expense | B8: 20000
A9: Change in Accounts Receivable | B9: -15000
A10: Change in Food Inventory | B10: -25000
A11: Change in Supplies | B11: 5000
A12: Change in Accounts Payable | B12: 10000
A13: Change in Accrued Expenses | B13: 5000
A14: Net Cash from Operating Activities | B14: =B5+SUM(B8:B13) -> 1015000
A16: INVESTING ACTIVITIES
A17: Purchase of Equipment | B17: -75000
A18: Purchase of Vehicles | B18: -50000
A19: Proceeds from Sale of Equipment | B19: 5000
A20: Net Cash from Investing Activities | B20: =SUM(B17:B19) -> -120000
A22: FINANCING ACTIVITIES
A23: Proceeds from Loan/Grants | B23: 100000
A24: Loan Repayments | B24: -25000
A25: Donations (Restricted Funds) | B25: 50000
A26: Net Cash from Financing Activities | B26: =SUM(B23:B25) -> 125000
A28: Net Increase/(Decrease) in Cash | B28: =B14+B20+B26 -> 1020000 | C28: 1,015,000+(-120,000)+125,000
A30: Cash at Beginning of Year | B30: 300000
A31: Cash at End of Year | B31: =B30+B28 -> 1320000 | C31: 1,020,000+300,0000
