Workbook

Sheet Dashboard
A1: CALGARY FOOD BANK - FINANCIAL DASHBOARD
A3: FY2024 Financial Summary
A4: Metric | B4: Current | C4: Budget | D4: Variance | E4: Status
A5: Total Revenue | B5: =Revenue!B9 -> 2300000 | C5: 2250000 | D5: =B5-C5 -> 50000 | E5: On Track
A6: Total Expenses | B6: =Expenses!B14 -> 1285000 | C6: 1350000 | D6: =B6-C6 -> -65000 | E6: Under Budget
A7: Net Surplus | B7: =B5-B6 -> 1015000 | C7: 900000 | D7: =B7-C7 -> 115000 | E7: Excellent
A8: Operating Margin | B8: =B7/B5 -> 0.44130435 | C8: 0.4 | D8: =B8-C8 -> 0.041304348 | E8: Strong
A11: KEY PERFORMANCE INDICATORS
A12: KPI | B12: Current | C12: Target | D12: Assessment
A13: Program Expense Ratio | B13: =Programs!C9/B5 -> 0.27782609 | C13: 0.75 | D13: Conservative
A14: Admin Expense Ratio | B14: =50000/B5 -> 0.02173913 | C14: 0.15 | D14: Excellent
A15: Break-Even Revenue | B15: 661754 | C15: 700000 | D15: Strong Buffer
A16: Safety Margin % | B16: =(B5-661754)/B5 -> 0.71228087 | C16: 0.5 | D16: Very Strong
A17: Cost per Beneficiary | B17: =Programs!C9/Programs!D9 -> 45.642857 | C17: 50 | D17: On Track

Sheet Revenue
A1: REVENUE TRACKING - FY2024
A3: Revenue Source | B3: YTD | C3: Target | D3: % of Goal | E3: Trend
A4: Monetary Donations | B4: 1200000 | C4: 1150000 | D4: =B4/C4 -> 1.0434783 | E4: ↑ Growing
A5: In-Kind Donations | B5: 600000 | C5: 550000 | D5: =B5/C5 -> 1.0909091 | E5: ↑ Strong
A6: Government Grants | B6: 400000 | C6: 400000 | D6: =B6/C6 -> 1 | E6: → On Track
A7: Other Revenue | B7: 100000 | C7: 150000 | D7: =B7/C7 -> 0.66666667 | E7: ↓ Monitor
A9: TOTAL REVENUE | B9: =SUM(B4:B7) -> 2300000 | C9: =SUM(C4:C7) -> 2250000 | D9: =B9/C9 -> 1.0222222

Sheet Expenses
A1: EXPENSE TRACKING - FY2024
A3: Category | B3: Budgeted | C3: Actual YTD | D3: Remaining | E3: % Used | F3: Status
A4: Staff Salaries & Benefits | B4: 800000 | C4: 800000 | D4: =B4-C4 -> 0 | E4: =C4/B4 -> 1 | F4: =IF(E4<0.9,"OK",IF(E4<1,"Ok","At Limit")) -> At Limit
A5: Facility Rent/Lease | B5: 150000 | C5: 150000 | D5: =B5-C5 -> 0 | E5: =C5/B5 -> 1 | F5: =IF(E5<0.9,"OK",IF(E5<1,"Ok","At Limit")) -> At Limit
A6: Utilities & Maintenance | B6: 80000 | C6: 80000 | D6: =B6-C6 -> 0 | E6: =C6/B6 -> 1 | F6: =IF(E6<0.9,"OK",IF(E6<1,"Ok","At Limit")) -> At Limit
A7: Vehicles & Transportation | B7: 60000 | C7: 60000 | D7: =B7-C7 -> 0 | E7: =C7/B7 -> 1 | F7: =IF(E7<0.9,"OK",IF(E7<1,"Ok","At Limit")) -> At Limit
A8: Technology & Systems | B8: 40000 | C8: 40000 | D8: =B8-C8 -> 0 | E8: =C8/B8 -> 1 | F8: =IF(E8<0.9,"OK",IF(E8<1,"Ok","At Limit")) -> At Limit
A9: Admin & Office | B9: 50000 | C9: 45000 | D9: =B9-C9 -> 5000 | E9: =C9/B9 -> 0.9 | F9: =IF(E9<0.9,"OK",IF(E9<1,"Ok","At Limit")) -> Ok
A10: Marketing & Outreach | B10: 30000 | C10: 25000 | D10: =B10-C10 -> 5000 | E10: =C10/B10 -> 0.83333333 | F10: =IF(E10<0.9,"OK",IF(E10<1,"Ok","At Limit")) -> OK
A11: Food Storage & Distribution | B11: 75000 | C11: 75000 | D11: =B11-C11 -> 0 | E11: =C11/B11 -> 1 | F11: =IF(E11<0.9,"OK",IF(E11<1,"Ok","At Limit")) -> At Limit
A14: TOTAL EXPENSES | B14: =SUM(B4:B11) -> 1285000 | C14: =SUM(C4:C11) -> 1275000 | D14: =B14-C14 -> 10000 | E14: =C14/B14 -> 0.9922179 | F14: On Track

Sheet Programs
A1: PROGRAM ALLOCATION & IMPACT
A3: Program | B3: Budget | C3: Spending | D3: YTD Served | E3: Cost/Beneficiary | F3: % Complete
A4: Emergency Food Hampers | B4: 350000 | C4: 345000 | D4: 8500 | E4: =C4/D4 -> 40.588235 | F4: =C4/B4 -> 0.98571429
A5: Community Kitchen Programs | B5: 120000 | C5: 118000 | D5: 2200 | E5: =C5/D5 -> 53.636364 | F5: =C5/B5 -> 0.98333333
A6: Youth & Nutrition Education | B6: 85000 | C6: 82000 | D6: 1500 | E6: =C6/D6 -> 54.666667 | F6: =C6/B6 -> 0.96470588
A7: Seniors Support Initiative | B7: 95000 | C7: 94000 | D7: 1800 | E7: =C7/D7 -> 52.222222 | F7: =C7/B7 -> 0.98947368
A9: TOTAL PROGRAMS | B9: =SUM(B4:B7) -> 650000 | C9: =SUM(C4:C7) -> 639000 | D9: =SUM(D4:D7) -> 14000 | E9: =C9/D9 -> 45.642857

Sheet Monthly Tracker
A1: MONTHLY FINANCIAL TRACKING
A3: Month | B3: Revenue | C3: Expenses | D3: Surplus | E3: Cumulative
A4: January | B4: =Dashboard!$B$5/12 -> 191666.67 | C4: =Dashboard!$B$6/12 -> 107083.33 | D4: =B4-C4 -> 84583.333 | E4: =D4 -> 84583.333
A5: February | B5: =Dashboard!$B$5/12 -> 191666.67 | C5: =Dashboard!$B$6/12 -> 107083.33 | D5: =B5-C5 -> 84583.333 | E5: =D5+E4 -> 169166.67
A6: March | B6: =Dashboard!$B$5/12 -> 191666.67 | C6: =Dashboard!$B$6/12 -> 107083.33 | D6: =B6-C6 -> 84583.333 | E6: =D6+E5 -> 253750
A7: April | B7: =Dashboard!$B$5/12 -> 191666.67 | C7: =Dashboard!$B$6/12 -> 107083.33 | D7: =B7-C7 -> 84583.333 | E7: =D7+E6 -> 338333.33
A8: May | B8: =Dashboard!$B$5/12 -> 191666.67 | C8: =Dashboard!$B$6/12 -> 107083.33 | D8: =B8-C8 -> 84583.333 | E8: =D8+E7 -> 422916.67
A9: June | B9: =Dashboard!$B$5/12 -> 191666.67 | C9: =Dashboard!$B$6/12 -> 107083.33 | D9: =B9-C9 -> 84583.333 | E9: =D9+E8 -> 507500
A10: July | B10: =Dashboard!$B$5/12 -> 191666.67 | C10: =Dashboard!$B$6/12 -> 107083.33 | D10: =B10-C10 -> 84583.333 | E10: =D10+E9 -> 592083.33
A11: August | B11: =Dashboard!$B$5/12 -> 191666.67 | C11: =Dashboard!$B$6/12 -> 107083.33 | D11: =B11-C11 -> 84583.333 | E11: =D11+E10 -> 676666.67
A12: September | B12: =Dashboard!$B$5/12 -> 191666.67 | C12: =Dashboard!$B$6/12 -> 107083.33 | D12: =B12-C12 -> 84583.333 | E12: =D12+E11 -> 761250
A13: October | B13: =Dashboard!$B$5/12 -> 191666.67 | C13: =Dashboard!$B$6/12 -> 107083.33 | D13: =B13-C13 -> 84583.333 | E13: =D13+E12 -> 845833.33
A14: November | B14: =Dashboard!$B$5/12 -> 191666.67 | C14: =Dashboard!$B$6/12 -> 107083.33 | D14: =B14-C14 -> 84583.333 | E14: =D14+E13 -> 930416.67
A15: December | B15: =Dashboard!$B$5/12 -> 191666.67 | C15: =Dashboard!$B$6/12 -> 107083.33 | D15: =B15-C15 -> 84583.333 | E15: =D15+E14 -> 1015000
A16: Total | B16: =SUM(B4:B15) -> 2300000 | C16: =SUM(C4:C15) -> 1285000 | D16: =SUM(D4:D15) -> 1015000
