Workbook

Sheet Dashboard
B1: Apple Inc. — Financial Performance Dashboard
B2: Fiscal Years 2021–2026 · Source: Apple Inc. Form 10-K filings
B4: Total Revenue (FY2025) | E4: Revenue Growth (FY25 vs FY24) | H4: Gross Margin (FY2025) | K4: Top Segment (FY2025)
B5: ="$"&TEXT('Revenue, Gross Profit & Income'!B6,"0.0")&"B" -> $416.2B | E5: =TEXT(('Revenue, Gross Profit & Income'!B6-'Revenue, Gross Profit & Income'!B5)/'Revenue, Gross Profit & Income'!B5,"0.00%") -> 6.43% | H5: =TEXT('Revenue, Gross Profit & Income'!B22,"0.00%") -> 46.91% | K5: ="iPhone ($"&TEXT('Product Segment - Apple Revenue'!F2,"0.0")&"B)" -> iPhone ($209.6B)
B44: Source: Apple Inc. Form 10-K filings, FY2021–2025 | Prepared by Arushi Seth

Sheet Revenue, Gross Profit & Income
A1: Year | B1: Revenue | C1: Gross Profit | D1: Operating Income
A2: 2021 | B2: 365.817 | C2: 152.836 | D2: 108.949
A3: 2022 | B3: 394.328 | C3: 170.782 | D3: 119.437
A4: 2023 | B4: 383.285 | C4: 169.148 | D4: 114.301
A5: 2024 | B5: 391.035 | C5: 180.683 | D5: 123.05
A6: 2025 | B6: 416.161 | C6: 195.201 | D6: 133.05
A7: 2026 | B7: 451.442 | C7: 216.071 | D7: 147.366
A17: Year | B17: Gross Margin | C17: Operating Margin
A18: 2021 | B18: =C2/B2 -> 0.4177936 | C18: =D2/B2 -> 0.29782378
A19: 2022 | B19: =C3/B3 -> 0.43309631 | C19: =D3/B3 -> 0.30288744
A20: 2023 | B20: =C4/B4 -> 0.4413113 | C20: =D4/B4 -> 0.29821412
A21: 2024 | B21: =C5/B5 -> 0.4620635 | C21: =D5/B5 -> 0.31467771
A22: 2025 | B22: =C6/B6 -> 0.46905164 | C22: =D6/B6 -> 0.319708
A23: 2026 | B23: =C7/B7 -> 0.47862405 | C23: =D7/B7 -> 0.32643396
A31: Source: Apple Inc. Form 10-K filings, FY2021–2025

Sheet Product Segment - Apple Revenue
A1: Segment | B1: FY 2021 | C1: FY 2022 | D1: FY 2023 | E1: FY 2024 | F1: FY 2025
A2: iPhone | B2: 191.973 | C2: 205.485 | D2: 200.583 | E2: 201.183 | F2: 209.59
A3: Mac | B3: 35.19 | C3: 40.177 | D3: 29.357 | E3: 29.984 | F3: 33.71
A4: iPad | B4: 31.862 | C4: 29.292 | D4: 28.3 | E4: 26.694 | F4: 28.02
A5: Wearables/Home/Accessories | B5: 38.367 | C5: 41.241 | D5: 39.845 | E5: 37.005 | F5: 35.69
A6: Services | B6: 68.425 | C6: 78.129 | D6: 85.2 | E6: 96.169 | F6: 109.16
A25: Source: Apple Inc. Form 10-K filings, FY2021–2025

Sheet Region - Apple Revenue
A1: Region | B1: FY2021 | C1: FY2022 | D1: FY2023 | E1: FY2024 | F1: FY2025
A2: Americas | B2: 153.306 | C2: 169.658 | D2: 162.56 | E2: 167.05 | F2: 178.35
A3: Europe | B3: 89.307 | C3: 95.118 | D3: 94.294 | E3: 101.3 | F3: 111.03
A4: Greater China | B4: 68.366 | C4: 74.2 | D4: 72.559 | E4: 66.95 | F4: 64.38
A5: Japan | B5: 28.482 | C5: 25.977 | D5: 24.257 | E5: 25.05 | F5: 28.71
A6: Rest of Asia Pacific | B6: 26.356 | C6: 29.375 | D6: 29.615 | E6: 30.66 | F6: 33.71
A7: Total | B7: =SUM(B2:B6) -> 365.817 | C7: =SUM(C2:C6) -> 394.328 | D7: =SUM(D2:D6) -> 383.285 | E7: =SUM(E2:E6) -> 391.01 | F7: =SUM(F2:F6) -> 416.18
A24: Source: Apple Inc. Form 10-K filings, FY2021–2025

Sheet KIP cards
B1: Apple Inc. — Key Performance Indicators
B2: Total Revenue (FY2025) | E2: Revenue Growth (FY25 vs FY24) | H2: Gross Margin (FY2025) | K2: Top Segment (FY2025)
B3: ="$"&TEXT('Revenue, Gross Profit & Income'!B6,"0.0")&"B" -> $416.2B | E3: =TEXT(('Revenue, Gross Profit & Income'!B6-'Revenue, Gross Profit & Income'!B5)/'Revenue, Gross Profit & Income'!B5,"0.00%") -> 6.43% | H3: =TEXT('Revenue, Gross Profit & Income'!B22,"0.00%") -> 46.91% | K3: ="iPhone ($"&TEXT('Product Segment - Apple Revenue'!F2,"0.0")&"B)" -> iPhone ($209.6B)
